{"title": "Turquie : un uniforme special pour les journalistes emprisonnes", "newspaper": "Le Monde", "author": "EN LIVE", "date_publi": "2017-12-29", "content": " Ces tenues devront etre portees lors de leur proces, << au mepris de la presomption d'innocence >>, s'inquiete Reporters sans frontieres. Le Monde | 29.12.2017 a 16h05 * Mis a jour le\n29.12.2017 a 16h14 Lire aussi : En Turquie, la purge sans fin Ce decret, qui devrait entrer en application d'ici un mois, pourrait concerner << plus de 58 000 detenus >>, dont << des dizaines de journalistes >>, s'alarme RSF. << Au mepris de la presomption d'innocence, les journalistes emprisonnes seront ainsi assimiles aux putschistes responsables du bain de sang du 15 juillet 2016, met en garde le secretaire general de l'ONG, Christophe Deloire. Nous demandons l'abrogation immediate de ce decret-loi, qui participe de la derive de la justice turque vers un instrument de vengeance politique. >> Reporters sans frontieres estime << probable >> que de nombreux prisonniers refusent de porter cet uniforme stigmatisant, << avec des consequences inconnues, comme leur exclusion du tribunal >>. RSF rappelle que dans les annees 1980 l'obligation de porter un uniforme avait entraine des vagues de greves de la faim, qui avaient fait plusieurs victimes parmi les prisonniers politiques turcs. Abonnez-vous a partir de 1 EUR Le monde abonnements Profitez du journal ou et quand vous voulez. Abonnements papier, offres 100 % numeriques sur Web et tablette. S'abonner au Monde a partir de 1 EUR Journal d'information en ligne, Le Monde.fr offre a ses visiteurs un panorama complet de l'actualite. Decouvrez chaque jour toute l'info en direct (de la politique a l'economie en passant par le sport et la meteo) sur Le Monde.fr, le site de news leader de la presse francaise en ligne. Ces tenues devront etre portees lors de leur proces, << au mepris de la presomption d'innocence >>, s'inquiete Reporters sans frontieres. Le Monde | 29.12.2017 a 16h05 * Mis a jour le\n29.12.2017 a 16h14 Lire aussi : En Turquie, la purge sans fin Ce decret, qui devrait entrer en application d'ici un mois, pourrait concerner << plus de 58 000 detenus >>, dont << des dizaines de journalistes >>, s'alarme RSF. << Au mepris de la presomption d'innocence, les journalistes emprisonnes seront ainsi assimiles aux putschistes responsables du bain de sang du 15 juillet 2016, met en garde le secretaire general de l'ONG, Christophe Deloire. Nous demandons l'abrogation immediate de ce decret-loi, qui participe de la derive de la justice turque vers un instrument de vengeance politique. >> Reporters sans frontieres estime << probable >> que de nombreux prisonniers refusent de porter cet uniforme stigmatisant, << avec des consequences inconnues, comme leur exclusion du tribunal >>. RSF rappelle que dans les annees 1980 l'obligation de porter un uniforme avait entraine des vagues de greves de la faim, qui avaient fait plusieurs victimes parmi les prisonniers politiques turcs. Abonnez-vous a partir de 1 EUR Ces tenues devront etre portees lors de leur proces, << au mepris de la presomption d'innocence >>, s'inquiete Reporters sans frontieres. Le Monde | 29.12.2017 a 16h05 * Mis a jour le\n29.12.2017 a 16h14 Lire aussi : En Turquie, la purge sans fin Ce decret, qui devrait entrer en application d'ici un mois, pourrait concerner << plus de 58 000 detenus >>, dont << des dizaines de journalistes >>, s'alarme RSF. << Au mepris de la presomption d'innocence, les journalistes emprisonnes seront ainsi assimiles aux putschistes responsables du bain de sang du 15 juillet 2016, met en garde le secretaire general de l'ONG, Christophe Deloire. Nous demandons l'abrogation immediate de ce decret-loi, qui participe de la derive de la justice turque vers un instrument de vengeance politique. >> Reporters sans frontieres estime << probable >> que de nombreux prisonniers refusent de porter cet uniforme stigmatisant, << avec des consequences inconnues, comme leur exclusion du tribunal >>. RSF rappelle que dans les annees 1980 l'obligation de porter un uniforme avait entraine des vagues de greves de la faim, qui avaient fait plusieurs victimes parmi les prisonniers politiques turcs. Abonnez-vous a partir de 1 EUR Ces tenues devront etre portees lors de leur proces, << au mepris de la presomption d'innocence >>, s'inquiete Reporters sans frontieres. Le Monde | 29.12.2017 a 16h05 * Mis a jour le\n29.12.2017 a 16h14 Lire aussi : En Turquie, la purge sans fin Ce decret, qui devrait entrer en application d'ici un mois, pourrait concerner << plus de 58 000 detenus >>, dont << des dizaines de journalistes >>, s'alarme RSF. << Au mepris de la presomption d'innocence, les journalistes emprisonnes seront ainsi assimiles aux putschistes responsables du bain de sang du 15 juillet 2016, met en garde le secretaire general de l'ONG, Christophe Deloire. Nous demandons l'abrogation immediate de ce decret-loi, qui participe de la derive de la justice turque vers un instrument de vengeance politique. >> Reporters sans frontieres estime << probable >> que de nombreux prisonniers refusent de porter cet uniforme stigmatisant, << avec des consequences inconnues, comme leur exclusion du tribunal >>. RSF rappelle que dans les annees 1980 l'obligation de porter un uniforme avait entraine des vagues de greves de la faim, qui avaient fait plusieurs victimes parmi les prisonniers politiques turcs. Abonnez-vous a partir de 1 EUR Ces tenues devront etre portees lors de leur proces, << au mepris de la presomption d'innocence >>, s'inquiete Reporters sans frontieres. Le Monde | 29.12.2017 a 16h05 * Mis a jour le\n29.12.2017 a 16h14 Lire aussi : En Turquie, la purge sans fin Ce decret, qui devrait entrer en application d'ici un mois, pourrait concerner << plus de 58 000 detenus >>, dont << des dizaines de journalistes >>, s'alarme RSF. << Au mepris de la presomption d'innocence, les journalistes emprisonnes seront ainsi assimiles aux putschistes responsables du bain de sang du 15 juillet 2016, met en garde le secretaire general de l'ONG, Christophe Deloire. Nous demandons l'abrogation immediate de ce decret-loi, qui participe de la derive de la justice turque vers un instrument de vengeance politique. >> Reporters sans frontieres estime << probable >> que de nombreux prisonniers refusent de porter cet uniforme stigmatisant, << avec des consequences inconnues, comme leur exclusion du tribunal >>. RSF rappelle que dans les annees 1980 l'obligation de porter un uniforme avait entraine des vagues de greves de la faim, qui avaient fait plusieurs victimes parmi les prisonniers politiques turcs. Ces tenues devront etre portees lors de leur proces, << au mepris de la presomption d'innocence >>, s'inquiete Reporters sans frontieres. Le Monde | 29.12.2017 a 16h05 * Mis a jour le\n29.12.2017 a 16h14 Lire aussi : En Turquie, la purge sans fin Ce decret, qui devrait entrer en application d'ici un mois, pourrait concerner << plus de 58 000 detenus >>, dont << des dizaines de journalistes >>, s'alarme RSF. << Au mepris de la presomption d'innocence, les journalistes emprisonnes seront ainsi assimiles aux putschistes responsables du bain de sang du 15 juillet 2016, met en garde le secretaire general de l'ONG, Christophe Deloire. Nous demandons l'abrogation immediate de ce decret-loi, qui participe de la derive de la justice turque vers un instrument de vengeance politique. >> Reporters sans frontieres estime << probable >> que de nombreux prisonniers refusent de porter cet uniforme stigmatisant, << avec des consequences inconnues, comme leur exclusion du tribunal >>. RSF rappelle que dans les annees 1980 l'obligation de porter un uniforme avait entraine des vagues de greves de la faim, qui avaient fait plusieurs victimes parmi les prisonniers politiques turcs. Lire aussi : En Turquie, la purge sans fin Ce decret, qui devrait entrer en application d'ici un mois, pourrait concerner << plus de 58 000 detenus >>, dont << des dizaines de journalistes >>, s'alarme RSF. << Au mepris de la presomption d'innocence, les journalistes emprisonnes seront ainsi assimiles aux putschistes responsables du bain de sang du 15 juillet 2016, met en garde le secretaire general de l'ONG, Christophe Deloire. Nous demandons l'abrogation immediate de ce decret-loi, qui participe de la derive de la justice turque vers un instrument de vengeance politique. >> Reporters sans frontieres estime << probable >> que de nombreux prisonniers refusent de porter cet uniforme stigmatisant, << avec des consequences inconnues, comme leur exclusion du tribunal >>. RSF rappelle que dans les annees 1980 l'obligation de porter un uniforme avait entraine des vagues de greves de la faim, qui avaient fait plusieurs victimes parmi les prisonniers politiques turcs. Abonnez-vous a partir de 1 EUR Abonnez-vous a partir de 1 EUR Le monde abonnements Profitez du journal ou et quand vous voulez. Abonnements papier, offres 100 % numeriques sur Web et tablette. S'abonner au Monde a partir de 1 EUR Le monde abonnements Profitez du journal ou et quand vous voulez. Abonnements papier, offres 100 % numeriques sur Web et tablette. S'abonner au Monde a partir de 1 EUR Le monde abonnements Profitez du journal ou et quand vous voulez. Abonnements papier, offres 100 % numeriques sur Web et tablette. S'abonner au Monde a partir de 1 EUR ", "theme": "Forum"}