{"title": "Pascal Agrapart : Monsieur terroir", "newspaper": "Le Monde", "author": ["Remi Barroux"], "date_publi": "2017-12-15", "content": "A Avize, village classe grand cru de la cote des Blancs, la concurrence est rude. Mais Pascal Agrapart, 55 ans, aide de sa femme Nathalie et dorenavant de son fils Ambroise, creuse son sillon - il le fit un temps au cul de sa jument Venus, aujourd'hui disparue mais qui donne son nom a une belle cuvee 100 % chardonnay. Pascal fait ses  vins  en pensant d'abord a  mettre  en valeur les terroirs. Il le peut ; 80 % de ses 12 hectares sont en grands crus (a Avize, Cramant, Oger et Oiry), et hormis 5 % en pinot noir, tout est en chardonnay. Ne pas  agresser  le sol Amoureux de ses terres, le vigneron les respecte.  << Ne pas agresser le sol, c'est  eviter  les desherbants. Une terre perenne a besoin d'oxygene, de vie microbienne, de nutriments >> , egrene Pascal Agrapart. Alors, il griffe les sols en surface pour eviter l'enherbement qui concurrencerait la vigne, il les traite mecaniquement, et il use de cuivre et de soufre plutot que de chimie. Disons-le, il est bio comme M. Jourdain fait de la prose, mais ne souhaite pas de certification. << Je ne veux pas m'interdire l'utilisation d'une molecule de synthese si les conditions climatiques l'imposent. Pourfaire du vin, il faut du raisin,  argumente-t-il.  Moi, je me soigne avec l'homeopathie, je mise sur le preventif, mais si j'avais un truc grave, un  cancer , je prendrais le traitement adequat .  >> Typicites des terroirs en sept cuvees En 1982, Pascal Agrapart reprend les renes du domaine (quatre generations) et sort sa premiere cuvee en 1985. Depuis, le vigneron, regard clair et  sourire  conquerant, propose chaque annee quelque 100 000 bouteilles - attention, tout est vendu sur allocation. Pascal decline sa passion pour les terroirs, leurs typicites, en sept cuvees, ou le chardonnay est souverain. Outre les cuvees << 7 crus >> ou << Terroirs >>, avouons un coup de coeur pour la << Complantee >>, chardonnay et pinot noir assembles avec les anciens petit meslier, arbanne ou encore pinot blanc, complexe a souhait (3 500 flacons, 42 euros) ou encore la << Mineral >> 2011, un blanc de blancs extra-brut, magnifique de tension et de precision (56 euros). Et, dans quelques semaines, les amateurs de beaux raisins pourront  gouter  le millesime 2008, une splendeur (150 euros).", "theme": "vins"}