{"title": "Femmes a l'Assemblee : vers la parite ?", "newspaper": "Liberation", "author": ["Constance Daire"], "date_publi": "2017-06-12", "content": "Dimanche, 246 candidates sont arrivees en tete au  premier tour des elections legislatives , contre 331 hommes. Si elles sont elues le 18 juin, il s'agirait d'un record historique pour l'Assemblee, qui serait alors composee a 42,5% de deputees. La raison de cette evolution ? La Republique en marche, grand vainqueur du premier tour, presentait 52% de candidates pour ces legislatives. Le parti d'Emmanuel Macron a donc ainsi porte 192 femmes en tete au second tour pour 207 hommes. Le Modem, son partenaire, est aussi quasi paritaire avec 25 femmes arrivees premieres pour 27 hommes. De leur cote, les femmes issues du parti Les Republicains sont largement sous-representees : 9 d'entre elles sont au premier rang dans leur circonscription contre 40 candidats masculins. Les autres mauvais eleves, le FN et l'UDI, affichent respectivement 6 femmes en tete contre 14 hommes pour le premier et 2 candidates contre 10 pour le deuxieme. La gauche presente quant a elle une parite variable pour le second tour, due aussi aux nombreuses defaites de ses candidats. Si 70 femmes accedent au second tour contre 101 hommes, le nombre de celles arrivees en tete est faible : 4 femmes contre 7 hommes pour le PS, une femme contre deux hommes pour la France insoumise, 3 femmes pour 7 hommes etiquetes divers gauche et une femme pour 4 hommes pour le PCF et une femme pour un homme au Parti radical de gauche (PRG). Chez les divers droite, on compte 2 femmes pour 4 hommes en tete au premier tour. En tout, 460 femmes seront presentes au second tour, face a 694 hommes pour un total de 1154 candidats. 214 candidates sont en effet arrivees deuxieme. Si elles parviennent a se hisser en tete au second tour, on pourrait meme depasser les 42,5% de deputees a l'Assemblee. Autre point positif : selon les circonscriptions qui voient s'opposer deux femmes, 83 sieges seront de facon certaine occupes par des deputees a l'issue de ces legislatives... ce qui reste nettement inferieur aux 200 circonscriptions qui voient s'opposer deux hommes et porteront un depute a l'Assemblee. Meme si cette election ne signe probablement pas l'avenement de la parite totale a l'Assemblee, elle represente une avancee historique. En comparaison,  en 2012, 155 femmes avaient ete elues  au second tour et representaient alors 26,86% de sieges. Ce score, deja salue il y a cinq ans, restait relativement faible par rapport aux autres pays europeens, d'apres le  classement de la fondation Robert Schuman . Mais ces progressions s'inscrivent dans un contexte d'evolution societale favorable a une meilleure representation des femmes, dont  le nombre de sieges a l'Assemblee  ne cesse d'augmenter depuis 1968.   Retrouvez  les resultats de la presidentielle  par ville et par departement et tous  les resultats  des scrutins precedents.\n            ", "theme": "elections presidentielle legislatives 2017"}